{
	"configurations" : 
	[
		{
			"directories" : 
			[
				{
					"build" : ".",
					"jsonFile" : "directory-.-Debug-f5ebdc15457944623624.json",
					"minimumCMakeVersion" : 
					{
						"string" : "3.24"
					},
					"projectIndex" : 0,
					"source" : ".",
					"targetIndexes" : 
					[
						0
					]
				}
			],
			"name" : "Debug",
			"projects" : 
			[
				{
					"directoryIndexes" : 
					[
						0
					],
					"name" : "BaseTest",
					"targetIndexes" : 
					[
						0
					]
				}
			],
			"targets" : 
			[
				{
					"directoryIndex" : 0,
					"id" : "BaseTest::@6890427a1f51a3e7e1df",
					"jsonFile" : "target-BaseTest-Debug-5109659e2be6bd395e59.json",
					"name" : "BaseTest",
					"projectIndex" : 0
				}
			]
		}
	],
	"kind" : "codemodel",
	"paths" : 
	{
		"build" : "/home/master/ProgramFiles/ClionProjects/BaseTest/cmake-build-debug",
		"source" : "/home/master/ProgramFiles/ClionProjects/BaseTest"
	},
	"version" : 
	{
		"major" : 2,
		"minor" : 4
	}
}
